README.md
setup.py
NCHU_nlptoolkit/__init__.py
NCHU_nlptoolkit.egg-info/PKG-INFO
NCHU_nlptoolkit.egg-info/SOURCES.txt
NCHU_nlptoolkit.egg-info/dependency_links.txt
NCHU_nlptoolkit.egg-info/requires.txt
NCHU_nlptoolkit.egg-info/top_level.txt
NCHU_nlptoolkit.egg-info/zip-safe
NCHU_nlptoolkit/scripts/dump2es.py
NCHU_nlptoolkit/cut/2023_stopword.pkl
NCHU_nlptoolkit/cut/__init__.py
NCHU_nlptoolkit/cut/stopwords-en.pkl
NCHU_nlptoolkit/dictionary/__init__.py
NCHU_nlptoolkit/dictionary/attractions.dict.txt
NCHU_nlptoolkit/dictionary/dcard.dict.txt
NCHU_nlptoolkit/dictionary/dict.txt.big.txt
NCHU_nlptoolkit/dictionary/law.txt
NCHU_nlptoolkit/dictionary/ptt.txt
NCHU_nlptoolkit/dictionary/wiki_title_traditional.txt
NCHU_nlptoolkit/scripts/dump2es.py