Metadata-Version: 2.1
Name: NCHU-nlptoolkit
Version: 2.0.4
Summary: nlplab dictionary, stopwords module
Home-page: 
Download-URL: 
Author: ['davidtnfsh', 'CYJiang0718', 'dancheng', 'puppy']
Author-email: nlpnchu@gmail.com
License: GPL3.0
Keywords: NCHU_nlptoolkit,jieba,dictionary,stopwords
